dewloosh/geom/H27.py
dewloosh/geom/H8.py
dewloosh/geom/Q4.py
dewloosh/geom/Q9.py
dewloosh/geom/T3.py
dewloosh/geom/T6.py
dewloosh/geom/TET4.py
dewloosh/geom/__init__.py
dewloosh/geom/cell.py
dewloosh/geom/celldata.py
dewloosh/geom/coordarray.py
dewloosh/geom/frame.py
dewloosh/geom/line.py
dewloosh/geom/mesh1d.py
dewloosh/geom/polydata.py
dewloosh/geom/polygon.py
dewloosh/geom/polyhedron.py
dewloosh/geom/pop.py
dewloosh/geom/rgrid.py
dewloosh/geom/tile.py
dewloosh/geom/utils.py
dewloosh/geom/vtkcelltypes.py
dewloosh/geom/vtkutils.py
dewloosh/geom/space/__init__.py
dewloosh/geom/space/frame.py
dewloosh/geom/space/utils.py
dewloosh/geom/tet/__init__.py
dewloosh/geom/tet/tetmesh.py
dewloosh/geom/tet/tetutils.py
dewloosh/geom/topo/__init__.py
dewloosh/geom/topo/topo.py
dewloosh/geom/topo/topodata.py
dewloosh/geom/topo/topologyarray.py
dewloosh/geom/topo/tr.py
dewloosh/geom/tri/__init__.py
dewloosh/geom/tri/triang.py
dewloosh/geom/tri/trimesh.py
dewloosh/geom/tri/triplot.py
dewloosh/geom/tri/triutils.py
dewloosh.geom-0.0.dev8.dist-info/LICENSE
dewloosh.geom-0.0.dev8.dist-info/METADATA
dewloosh.geom-0.0.dev8.dist-info/WHEEL
dewloosh.geom-0.0.dev8.dist-info/top_level.txt
dewloosh.geom-0.0.dev8.dist-info/RECORD
