Metadata-Version: 2.1
Name: dewloosh.geom
Version: 0.0.dev8
Summary: A pure python package to build, manipulate and analyze polygonal meshes.
Home-page: https://github.com/dewloosh/dewloosh-geom
Author: dewloosh
Author-email: dewloosh@gmail.com
License: UNKNOWN
Download-URL: https://github.com/dewloosh/dewloosh-geom/archive/refs/tags/0.0.dev8.zip
Platform: UNKNOWN
Classifier: Development Status :: 3 - Alpha
Classifier: License :: OSI Approved :: MIT License
Classifier: Programming Language :: Python :: 3
Classifier: Operating System :: OS Independent
Requires-Python: >=3.6
Requires-Dist: dewloosh.math
Requires-Dist: matplotlib
Requires-Dist: pyvista
